ga_attribution_scrape/__init__.py
ga_attribution_scrape/scrape.py
ga_attribution_scrape-0.2.1.dist-info/METADATA
ga_attribution_scrape-0.2.1.dist-info/WHEEL
ga_attribution_scrape-0.2.1.dist-info/top_level.txt
ga_attribution_scrape-0.2.1.dist-info/RECORD
