Metadata-Version: 2.1
Name: ga-attribution-scrape
Version: 0.2.1
Summary: Scrapes attribution data from GAs Model Comparison Tool through JS Network and sends to Bigquery.
Home-page: https://github.com/lewisaustinbryan/ga-attribution-scrape
Author: Lewis Bryan
Author-email: lewis.a.bryan@googlemail.com
License: UNKNOWN
Platform: UNKNOWN
Classifier: Programming Language :: Python :: 3
Classifier: License :: OSI Approved :: MIT License
Requires-Python: >=3.6
Requires-Dist: google-auth
Requires-Dist: google-api-python-client
Requires-Dist: google-cloud-bigquery
Requires-Dist: oauth2client
Requires-Dist: pandas-gbq
Requires-Dist: pandas
Requires-Dist: tqdm
